nice_go/__init__.py
nice_go/_authentication_tokens.py
nice_go/_aws_cognito_authenticator.py
nice_go/_barrier.py
nice_go/_const.py
nice_go/_exceptions.py
nice_go/_util.py
nice_go/_ws_client.py
nice_go/nice_go_api.py
nice_go/py.typed
nice_go-1.0.1.dist-info/LICENSE
nice_go-1.0.1.dist-info/METADATA
nice_go-1.0.1.dist-info/WHEEL
nice_go-1.0.1.dist-info/RECORD
