Metadata-Version: 2.3
Name: nice-go
Version: 1.0.1
Summary: Control various Nice access control products
License: MIT
Author: IceBotYT
Author-email: 34712694+IceBotYT@users.noreply.github.com
Requires-Python: >=3.9.1,<4.0
Classifier: Development Status :: 4 - Beta
Classifier: Intended Audience :: Developers
Classifier: License :: OSI Approved :: MIT License
Classifier: Operating System :: OS Independent
Classifier: Programming Language :: Python
Classifier: Programming Language :: Python :: 3
Classifier: Programming Language :: Python :: 3.10
Classifier: Programming Language :: Python :: 3.11
Classifier: Programming Language :: Python :: 3.12
Classifier: Programming Language :: Python :: 3.13
Classifier: Programming Language :: Python :: 3.9
Classifier: Topic :: Software Development :: Libraries :: Python Modules
Classifier: Typing :: Typed
Requires-Dist: aiobotocore (>=2.13.1,<3.0.0)
Requires-Dist: aiohttp (>=3.9.5,<4.0.0)
Requires-Dist: pycognito (>=2024.5.1,<2025.0.0)
Requires-Dist: tenacity (>=8.5.0,<9.0.0)
Requires-Dist: yarl (>=1.9.4,<2.0.0)
Project-URL: Documentation, https://IceBotYT.github.io/nice-go
Project-URL: Homepage, https://IceBotYT.github.io/nice-go
Project-URL: Repository, https://github.com/IceBotYT/nice-go
